{
  "run_id": "bt_1784726605",
  "started_at": "2026-07-22T13:23:25.656393+00:00",
  "config": {
    "horizon_days": 7,
    "min_days_for_validity": 60
  },
  "sufficient_sample": false,
  "sample_days": 8,
  "sample_note": "only 8 distinct collection days on record; need >= 60 across multiple regimes before ANY number below should be trusted",
  "walk_forward_folds": [],
  "overall_dry_run_preview": {
    "n_rows": 3467,
    "n_with_forward_return": 357,
    "horizon_days": 7,
    "trend_score_vs_forward_return": {
      "spearman": -0.024,
      "hit_rate_60plus": {
        "precision": 0.391,
        "recall": 0.135,
        "predicted_positive": 46,
        "actual_positive": 133,
        "true_positive": 18,
        "n": 357
      },
      "hit_rate_below_40": {
        "precision": 0.621,
        "recall": 0.585,
        "predicted_positive": 211,
        "actual_positive": 224,
        "true_positive": 131,
        "n": 357
      }
    },
    "entry_grade_vs_forward_return": null,
    "entry_grade_note": "no rows carried an entry_timing grade in this window",
    "by_regime": {
      "SIDEWAYS": {
        "n": 357,
        "spearman": -0.024
      }
    }
  }
}